<?xml version="1.0" encoding="utf-8"?>
<!--Detailed report on module LeaveBalance-->
<CCCC_Project>
<module_summary>
<lines_of_code value="107" level="0" />
<lines_of_code_per_member_function value="******" level="0" />
<McCabes_cyclomatic_complexity value="22" level="0" />
<McCabes_cyclomatic_complexity_per_member_function value="******" level="2" />
<lines_of_code value="51" level="0" />
<lines_of_code_per_member_function value="********" level="2" />
<lines_of_code_per_line_of_comment value="2.098" level="0" />
<McCabes_cyclomatic_complexity_per_line_of_comment value="0.431" level="0" />
<weighted_methods_per_class_unity value="7" level="0" />
<weighted_methods_per_class_visibility value="7" level="0" />
<depth_of_inheritance_tree value="0" level="0" />
<number_of_children value="0" level="0" />
<coupling_between_objects value="7" level="0" />
<IF4 value="100" level="0" />
<IF4_per_member_function value="********" level="2" />
<IF4_visible value="100" level="1" />
<IF4_visible_per_member_function value="********" level="2" />
<IF4_concrete value="0" level="0" />
<IF4_concrete_per_member_function value="********" level="0" />
</module_summary>
<module_detail>
<description>definition</description>
<source_reference file="leavebalance.h" line="8" />
<lines_of_code value="7" level="0" />
<McCabes_cyclomatic_complexity value="0" level="0" />
<lines_of_comment value="0" level="0" />
<lines_of_code_per_line_of_comment value="------" level="0" />
<McCabes_cyclomatic_complexity_per_line_of_comment value="------" level="0" />
</module_detail>
<procedural_detail>
<member_function>
<name>LeaveBalance(const QString &amp;)</name>
<extent>
<description>declaration</description>
<source_reference file="leavebalance.h" line="14" />
</extent>
<extent>
<description>definition</description>
<source_reference file="leavebalance.cpp" line="15" />
</extent>
<lines_of_code value="8" level="0" />
<McCabes_cyclomatic_complexity value="1" level="0" />
<lines_of_comment value="8" level="0" />
<lines_of_code_per_line_of_comment value="------" level="0" />
<McCabes_cyclomatic_complexity_per_line_of_comment value="------" level="0" />
</member_function>
<member_function>
<name>_getLeaveBalance(LeaveTypes)</name>
<extent>
<description>declaration</description>
<source_reference file="leavebalance.h" line="17" />
</extent>
<extent>
<description>definition</description>
<source_reference file="leavebalance.cpp" line="101" />
</extent>
<lines_of_code value="5" level="0" />
<McCabes_cyclomatic_complexity value="1" level="0" />
<lines_of_comment value="7" level="0" />
<lines_of_code_per_line_of_comment value="------" level="0" />
<McCabes_cyclomatic_complexity_per_line_of_comment value="------" level="0" />
</member_function>
<member_function>
<name>_getUserId()</name>
<extent>
<description>definition</description>
<source_reference file="leavebalance.h" line="21" />
</extent>
<lines_of_code value="3" level="0" />
<McCabes_cyclomatic_complexity value="1" level="0" />
<lines_of_comment value="0" level="0" />
<lines_of_code_per_line_of_comment value="------" level="0" />
<McCabes_cyclomatic_complexity_per_line_of_comment value="------" level="0" />
</member_function>
<member_function>
<name>_updateLeaveBalance(LeaveTypes,int,QString)</name>
<extent>
<description>declaration</description>
<source_reference file="leavebalance.h" line="16" />
</extent>
<extent>
<description>definition</description>
<source_reference file="leavebalance.cpp" line="88" />
</extent>
<lines_of_code value="7" level="0" />
<McCabes_cyclomatic_complexity value="0" level="0" />
<lines_of_comment value="10" level="0" />
<lines_of_code_per_line_of_comment value="------" level="0" />
<McCabes_cyclomatic_complexity_per_line_of_comment value="------" level="0" />
</member_function>
<member_function>
<name>displayLeaveBalance()</name>
<extent>
<description>declaration</description>
<source_reference file="leavebalance.h" line="18" />
</extent>
<extent>
<description>definition</description>
<source_reference file="leavebalance.cpp" line="110" />
</extent>
<lines_of_code value="4" level="0" />
<McCabes_cyclomatic_complexity value="0" level="0" />
<lines_of_comment value="5" level="0" />
<lines_of_code_per_line_of_comment value="------" level="0" />
<McCabes_cyclomatic_complexity_per_line_of_comment value="------" level="0" />
</member_function>
<member_function>
<name>loadBalanceFromFile()</name>
<extent>
<description>declaration</description>
<source_reference file="leavebalance.h" line="19" />
</extent>
<extent>
<description>definition</description>
<source_reference file="leavebalance.cpp" line="27" />
</extent>
<lines_of_code value="42" level="1" />
<McCabes_cyclomatic_complexity value="13" level="1" />
<lines_of_comment value="10" level="0" />
<lines_of_code_per_line_of_comment value="4.200" level="0" />
<McCabes_cyclomatic_complexity_per_line_of_comment value="1.300" level="0" />
</member_function>
<member_function>
<name>saveBalanceToFile(QString)</name>
<extent>
<description>declaration</description>
<source_reference file="leavebalance.h" line="20" />
</extent>
<extent>
<description>definition</description>
<source_reference file="leavebalance.cpp" line="122" />
</extent>
<lines_of_code value="31" level="1" />
<McCabes_cyclomatic_complexity value="6" level="0" />
<lines_of_comment value="11" level="0" />
<lines_of_code_per_line_of_comment value="2.818" level="0" />
<McCabes_cyclomatic_complexity_per_line_of_comment value="0.545" level="0" />
</member_function>
</procedural_detail>
<structural_detail>
<module>
<name>LeaveBalance</name>
<client_module>
<name>Director</name>
<visible>true</visible>
<concrete>false</concrete>
<extent>
<description>pass by reference</description>
<source_reference file="director.h" line="11" />
</extent>
<extent>
<description>pass by reference</description>
<source_reference file="director.cpp" line="14" />
</extent>
<name>Employee</name>
<visible>true</visible>
<concrete>false</concrete>
<extent>
<description>has by reference</description>
<source_reference file="employee.h" line="27" />
</extent>
<extent>
<description>pass by reference</description>
<source_reference file="employee.h" line="31" />
</extent>
<extent>
<description>pass by reference</description>
<source_reference file="employee.cpp" line="3" />
</extent>
<name>Guard</name>
<visible>true</visible>
<concrete>false</concrete>
<extent>
<description>pass by reference</description>
<source_reference file="guard.h" line="24" />
</extent>
<extent>
<description>pass by reference</description>
<source_reference file="guard.cpp" line="4" />
</extent>
<name>LeaveApplication</name>
<visible>true</visible>
<concrete>false</concrete>
<extent>
<description>has by reference</description>
<source_reference file="leaveapplication.h" line="20" />
</extent>
<extent>
<description>pass by reference</description>
<source_reference file="leaveapplication.h" line="33" />
</extent>
<extent>
<description>pass by reference</description>
<source_reference file="leaveapplication.cpp" line="18" />
</extent>
<name>Supervisor</name>
<visible>true</visible>
<concrete>false</concrete>
<extent>
<description>pass by reference</description>
<source_reference file="supervisor.h" line="10" />
</extent>
<extent>
<description>pass by reference</description>
<source_reference file="supervisor.cpp" line="16" />
</extent>
</client_module>
<supplier_module>
<name>QString</name>
<visible>true</visible>
<concrete>true</concrete>
<extent>
<description>has by value</description>
<source_reference file="leavebalance.h" line="12" />
</extent>
<extent>
<description>pass by reference</description>
<source_reference file="leavebalance.h" line="14" />
</extent>
<extent>
<description>pass by value</description>
<source_reference file="leavebalance.h" line="16" />
</extent>
<extent>
<description>pass by value</description>
<source_reference file="leavebalance.h" line="20" />
</extent>
<extent>
<description>pass by reference</description>
<source_reference file="leavebalance.cpp" line="15" />
</extent>
<extent>
<description>pass by value</description>
<source_reference file="leavebalance.cpp" line="88" />
</extent>
<extent>
<description>pass by value</description>
<source_reference file="leavebalance.cpp" line="122" />
</extent>
<name>unordered_map</name>
<visible>true</visible>
<concrete>true</concrete>
<extent>
<description>has by value</description>
<source_reference file="leavebalance.h" line="11" />
</extent>
</supplier_module>
</module>
</structural_detail>
</CCCC_Project>
